ph_adorb/__init__.py
ph_adorb/adorb_cost.py
ph_adorb/constructions.py
ph_adorb/ep_sql_file.py
ph_adorb/equipment.py
ph_adorb/fuel.py
ph_adorb/grid_region.py
ph_adorb/measures.py
ph_adorb/national_emissions.py
ph_adorb/variant.py
ph_adorb/yearly_values.py
ph_adorb/from_HBJSON/__init__.py
ph_adorb/from_HBJSON/create_variant.py
ph_adorb/from_HBJSON/read_HBJSON_file.py
ph_adorb/run/__init__.py
ph_adorb/run/calc_HBJSON_ADORB_costs.py
ph_adorb/run/generate_ADORB_cost_graph.py
ph_adorb/tables/__init__.py
ph_adorb/tables/variant.py
PH_ADORB-0.0.9.dist-info/LICENSE
PH_ADORB-0.0.9.dist-info/METADATA
PH_ADORB-0.0.9.dist-info/WHEEL
PH_ADORB-0.0.9.dist-info/top_level.txt
PH_ADORB-0.0.9.dist-info/RECORD
