Metadata-Version: 2.1
Name: PH-ADORB
Version: 0.0.9
Summary: Calculate the ADORB cost for a Passive House building.
Author-email: Ed May <phtools@bldgtyp.com>
Maintainer-email: Ed May <phtools@bldgtyp.com>
License: GNU
Project-URL: homepage, https://www.passivehousetools.com/
Project-URL: repository, https://github.com/PH-Tools/PH_ADORB/tree/main
Keywords: Honeybee,Honeybee-Energy,Passive House,Building Retrofit,Architecture,Energy Modeling,PHIUS,ADORB,Carbon Emissions,Embodied Carbon,Embodied CO2
Classifier: Programming Language :: Python :: 3
Classifier: License :: OSI Approved :: GNU General Public License v3 (GPLv3)
Classifier: Operating System :: OS Independent
Requires-Python: >=3.10
License-File: LICENSE
Requires-Dist: honeybee-energy>=1.109.17
Requires-Dist: honeybee-revive>=0.0.9
Requires-Dist: pandas>=2.2.3
Requires-Dist: plotly>=5.24.1
Requires-Dist: ph-units>=1.5.16
Requires-Dist: rich>=13.8.1
Provides-Extra: dev
Requires-Dist: black; extra == "dev"
Requires-Dist: isort; extra == "dev"
Requires-Dist: pytest; extra == "dev"
Requires-Dist: coverage; extra == "dev"
